Workbook
Name Slicer_Age_Group: #N/A
Name Slicer_HBA1C_Result: #N/A
Name Slicer_Weight_status: #N/A

Sheet Customer Name
A1: Customer ID | B1: TITLE | C1: FIRST NAME | D1: LAST NAME
A2: ID1 | B2: Ms | C2: Kelly | D2: Hawks
A3: ID2 | B3: Mr | C3: Matthew D | D3: Lehner
A4: ID3 | B4: Mr | C4: Phil | D4: Lu
A5: ID4 | B5: Ms | C5: Kelsey | D5: Osborne
A6: ID5 | B6: Ms | C6: Kristyn | D6: Kadala
A7: ID6 | B7: Mr | C7: Russell B | D7: Baker
A8: ID7 | B8: Mr | C8: Scott | D8: Macpherson
A9: ID8 | B9: Mr | C9: Stephen | D9: Hallman
A10: ID9 | B10: Mr | C10: Patrick R | D10: Moran
A11: ID10 | B11: Ms | C11: Brooke N | D11: Benner
A12: ID11 | B12: Ms | C12: Paola Andrea | D12: Fierro Vargas
... A2336: ID2335 | B2336: Mr | C2336: Aaron K | D2336: German

Sheet Medical Examination
A1: Customer ID | B1: BMI | C1: HBA1C | D1: HEART ISSUES | E1: ANY TRANSPLANT | F1: CANCER HISTORY | G1: No. of Surgeries | H1: SMOKER | I1: HBA1C Result | J1: Weight status
A2: ID1 | B2: 47.4 | C2: 7.47 | D2: No | E2: No | F2: No | G2: 0 | H2: Yes | I2: Diabetes | J2: Obesity
A3: ID2 | B3: 30.36 | C3: 5.77 | D3: No | E3: No | F3: No | G3: 0 | H3: Yes | I3: Prediabetes | J3: Obesity
A4: ID3 | B4: 34.485 | C4: 11.87 | D4: Yes | E4: No | F4: No | G4: 2 | H4: Yes | I4: Diabetes | J4: Obesity
A5: ID4 | B5: 38.095 | C5: 6.05 | D5: No | E5: No | F5: No | G5: 0 | H5: Yes | I5: Prediabetes | J5: Obesity
A6: ID5 | B6: 35.53 | C6: 5.45 | D6: No | E6: No | F6: No | G6: 0 | H6: Yes | I6: Normal | J6: Obesity
A7: ID6 | B7: 32.8 | C7: 6.59 | D7: No | E7: No | F7: No | G7: 0 | H7: Yes | I7: Diabetes | J7: Obesity
A8: ID7 | B8: 36.4 | C8: 6.07 | D8: No | E8: No | F8: No | G8: 0 | H8: Yes | I8: Prediabetes | J8: Obesity
A9: ID8 | B9: 36.96 | C9: 7.93 | D9: No | E9: No | F9: No | G9: 3 | H9: Yes | I9: Diabetes | J9: Obesity
A10: ID9 | B10: 41.14 | C10: 9.58 | D10: Yes | E10: No | F10: Yes | G10: 1 | H10: Yes | I10: Diabetes | J10: Obesity
A11: ID10 | B11: 38.06 | C11: 10.79 | D11: No | E11: No | F11: No | G11: 0 | H11: Yes | I11: Diabetes | J11: Obesity
A12: ID11 | B12: 37.7 | C12: 5.96 | D12: Yes | E12: No | F12: No | G12: 2 | H12: Yes | I12: Prediabetes | J12: Obesity
A13: ID12 | B13: 42.13 | C13: 11.9 | D13: No | E13: No | F13: No | G13: 0 | H13: Yes | I13: Diabetes | J13: Obesity
... A2336: ID2335 | B2336: 17.58 | C2336: 4.51 | D2336: No | E2336: No | F2336: No | G2336: 1 | H2336: No | I2336: Normal | J2336: Underweight

Sheet Hospitalisation
A1: Customer ID | B1: Date of Birth | C1: Age | D1: Children | E1: Charges | F1: hospital tire | G1: City Tire | H1: STATEID
A2: ID2335 | B2: 33794 | C2: 30 | D2: 0 | E2: 563.84 | F2: Tier - 2 | G2: Tier - 3 | H2: R1013
A3: ID2334 | B3: 33938 | C3: 30 | D3: 0 | E3: 570.62 | F3: Tier - 2 | G3: Tier - 1 | H3: R1013
A4: ID2333 | B4: 34150 | C4: 29 | D4: 0 | E4: 600 | F4: Tier - 2 | G4: Tier - 1 | H4: R1013
A5: ID2332 | B5: 33860 | C5: 30 | D5: 0 | E5: 604.54 | F5: Tier - 3 | G5: Tier - 3 | H5: R1013
A6: ID2331 | B6: 36003 | C6: 24 | D6: 0 | E6: 637.26 | F6: Tier - 3 | G6: Tier - 3 | H6: R1013
A7: ID2330 | B7: 37215 | C7: 21 | D7: 0 | E7: 646.14 | F7: Tier - 3 | G7: Tier - 3 | H7: R1012
A8: ID2329 | B8: 34121 | C8: 30 | D8: 0 | E8: 650 | F8: Tier - 3 | G8: Tier - 3 | H8: R1013
A9: ID2328 | B9: 34884 | C9: 27 | D9: 0 | E9: 650 | F9: Tier - 3 | G9: Tier - 3 | H9: R1013
A10: ID2327 | B10: 37589 | C10: 20 | D10: 0 | E10: 668 | F10: Tier - 3 | G10: Tier - 2 | H10: R1012
A11: ID2326 | B11: 35743 | C11: 25 | D11: 0 | E11: 670 | F11: Tier - 3 | G11: Tier - 3 | H11: R1013
A12: ID2325 | B12: 37146 | C12: 21 | D12: 0 | E12: 687.54 | F12: Tier - 3 | G12: Tier - 2 | H12: R1013
A13: ID2324 | B13: 36520 | C13: 23 | D13: 0 | E13: 700 | F13: Tier - 2 | G13: Tier - 3 | H13: R1013
... A2344: ID1 | B2344: 25123 | C2344: 54 | D2344: 0 | E2344: 63770.43 | F2344: Tier - 1 | G2344: Tier - 3 | H2344: R1013

Sheet Health Care
A1: Customer ID | B1: Title | C1: First Name | D1: Last Name | E1: Date of Birth | F1: Age | G1: Children | H1: BMI | I1: HBA1C | J1: Heart Issues | K1: ANY TRANSPLANT | L1: CANCER HISTORY | M1: No. of Surgeries | N1: SMOKER | O1: HBA1C Result | P1: Weight status | Q1: Charges | R1: Hospital Tire | S1: City Tire | T1: STATEID | U1: Age Group
A2: ID1 | B2: =_xlfn.XLOOKUP(Table4[[#This Row],[Customer ID]],Table1[[#This Row],[Customer ID]],Table1[[#This Row],[TITLE]],0) -> Ms | C2: {=_xlfn.XLOOKUP(Table4[[#This Row],[Customer ID]],Table1[[#All],[Customer ID]],Table1[[#All],[FIRST NAME]],0)} -> Kelly | D2: {=_xlfn.XLOOKUP(Table4[[#This Row],[Customer ID]],Table1[[#All],[Customer ID]],Table1[[#All],[LAST NAME]],0)} -> Hawks | E2: {=_xlfn.XLOOKUP(Table4[[#This Row],[Customer ID]],Table3[[#All],[Customer ID]],Table3[[#All],[Date of Birth]],0)} -> 25123 | F2: {=_xlfn.XLOOKUP(Table4[[#This Row],[Customer ID]],Table3[[#All],[Customer ID]],Table3[[#All],[Age]],0)} -> 54 | G2: {=_xlfn.XLOOKUP(Table4[[#This Row],[Customer ID]],Table3[[#All],[Customer ID]],Table3[[#All],[Children]],0)} -> 0 | H2: {=_xlfn.XLOOKUP(Table4[[#This Row],[Customer ID]],Table2[[#All],[Customer ID]],Table2[[#All],[BMI]],0)} -> 47.4 | I2: {=_xlfn.XLOOKUP(Table4[[#This Row],[Customer ID]],Table2[[#All],[Customer ID]],Table2[[#All],[HBA1C]],0)} -> 7.47 | J2: =_xlfn.XLOOKUP(Table4[[#This Row],[Customer ID]], 'Medical Examination'!A:A, 'Medical Examination'!D:D) -> No | K2: =_xlfn.XLOOKUP(Table4[[#This Row],[Customer ID]], 'Medical Examination'!A:A, 'Medical Examination'!E:E) -> No | L2: =_xlfn.XLOOKUP(Table4[[#This Row],[Customer ID]], 'Medical Examination'!A:A, 'Medical Examination'!F:F) -> No | M2: =_xlfn.XLOOKUP(Table4[[#This Row],[Customer ID]], 'Medical Examination'!A:A, 'Medical Examination'!G:G) -> 0 | N2: =_xlfn.XLOOKUP(Table4[[#This Row],[Customer ID]], 'Medical Examination'!A:A, 'Medical Examination'!H:H) -> Yes | O2: =_xlfn.XLOOKUP(Table4[[#This Row],[Customer ID]], 'Medical Examination'!A:A, 'Medical Examination'!I:I) -> Diabetes | P2: =_xlfn.XLOOKUP(Table4[[#This Row],[Customer ID]], 'Medical Examination'!A:A, 'Medical Examination'!J:J) -> Obesity | Q2: =_xlfn.XLOOKUP(Table4[[#This Row],[Customer ID]], Hospitalisation!A:A, Hospitalisation!E:E) -> 63770.43 | R2: =_xlfn.XLOOKUP(Table4[[#This Row],[Customer ID]], Hospitalisation!A:A, Hospitalisation!F:F) -> Tier - 1 | S2: =_xlfn.XLOOKUP(Table4[[#This Row],[Customer ID]], Hospitalisation!A:A, Hospitalisation!G:G) -> Tier - 3 | T2: =_xlfn.XLOOKUP(Table4[[#This Row],[Customer ID]], Hospitalisation!A:A, Hospitalisation!H:H) -> R1013 | U2: {=_xlfn.IFS(Table4[[#This Row],[Age]]<=29,"Youth",Table4[[#This Row],[Age]]<=49,"Adults",Table4[[#This Row],[Age]]>=50,"Senior")} -> Senior
A3: ID2 | B3: =_xlfn.XLOOKUP(Table4[[#This Row],[Customer ID]],Table1[[#This Row],[Customer ID]],Table1[[#This Row],[TITLE]],0) -> Mr | C3: {=_xlfn.XLOOKUP(Table4[[#This Row],[Customer ID]],Table1[[#All],[Customer ID]],Table1[[#All],[FIRST NAME]],0)} -> Matthew D | D3: {=_xlfn.XLOOKUP(Table4[[#This Row],[Customer ID]],Table1[[#All],[Customer ID]],Table1[[#All],[LAST NAME]],0)} -> Lehner | E3: {=_xlfn.XLOOKUP(Table4[[#This Row],[Customer ID]],Table3[[#All],[Customer ID]],Table3[[#All],[Date of Birth]],0)} -> 28284 | F3: {=_xlfn.XLOOKUP(Table4[[#This Row],[Customer ID]],Table3[[#All],[Customer ID]],Table3[[#All],[Age]],0)} -> 46 | G3: {=_xlfn.XLOOKUP(Table4[[#This Row],[Customer ID]],Table3[[#All],[Customer ID]],Table3[[#All],[Children]],0)} -> 0 | H3: {=_xlfn.XLOOKUP(Table4[[#This Row],[Customer ID]],Table2[[#All],[Customer ID]],Table2[[#All],[BMI]],0)} -> 30.36 | I3: {=_xlfn.XLOOKUP(Table4[[#This Row],[Customer ID]],Table2[[#All],[Customer ID]],Table2[[#All],[HBA1C]],0)} -> 5.77 | J3: =_xlfn.XLOOKUP(Table4[[#This Row],[Customer ID]], 'Medical Examination'!A:A, 'Medical Examination'!D:D) -> No | K3: =_xlfn.XLOOKUP(Table4[[#This Row],[Customer ID]], 'Medical Examination'!A:A, 'Medical Examination'!E:E) -> No | L3: =_xlfn.XLOOKUP(Table4[[#This Row],[Customer ID]], 'Medical Examination'!A:A, 'Medical Examination'!F:F) -> No | M3: =_xlfn.XLOOKUP(Table4[[#This Row],[Customer ID]], 'Medical Examination'!A:A, 'Medical Examination'!G:G) -> 0 | N3: =_xlfn.XLOOKUP(Table4[[#This Row],[Customer ID]], 'Medical Examination'!A:A, 'Medical Examination'!H:H) -> Yes | O3: =_xlfn.XLOOKUP(Table4[[#This Row],[Customer ID]], 'Medical Examination'!A:A, 'Medical Examination'!I:I) -> Prediabetes | P3: =_xlfn.XLOOKUP(Table4[[#This Row],[Customer ID]], 'Medical Examination'!A:A, 'Medical Examination'!J:J) -> Obesity | Q3: =_xlfn.XLOOKUP(Table4[[#This Row],[Customer ID]], Hospitalisation!A:A, Hospitalisation!E:E) -> 62592.87 | R3: =_xlfn.XLOOKUP(Table4[[#This Row],[Customer ID]], Hospitalisation!A:A, Hospitalisation!F:F) -> Tier - 2 | S3: =_xlfn.XLOOKUP(Table4[[#This Row],[Customer ID]], Hospitalisation!A:A, Hospitalisation!G:G) -> Tier - 3 | T3: =_xlfn.XLOOKUP(Table4[[#This Row],[Customer ID]], Hospitalisation!A:A, Hospitalisation!H:H) -> R1013 | U3: {=_xlfn.IFS(Table4[[#This Row],[Age]]<=29,"Youth",Table4[[#This Row],[Age]]<=49,"Adults",Table4[[#This Row],[Age]]>=50,"Senior")} -> Adults
A4: ID3 | B4: =_xlfn.XLOOKUP(Table4[[#This Row],[Customer ID]],Table1[[#This Row],[Customer ID]],Table1[[#This Row],[TITLE]],0) -> Mr | C4: {=_xlfn.XLOOKUP(Table4[[#This Row],[Customer ID]],Table1[[#All],[Customer ID]],Table1[[#All],[FIRST NAME]],0)} -> Phil | D4: {=_xlfn.XLOOKUP(Table4[[#This Row],[Customer ID]],Table1[[#All],[Customer ID]],Table1[[#All],[LAST NAME]],0)} -> Lu | E4: {=_xlfn.XLOOKUP(Table4[[#This Row],[Customer ID]],Table3[[#All],[Customer ID]],Table3[[#All],[Date of Birth]],0)} -> 25822 | F4: {=_xlfn.XLOOKUP(Table4[[#This Row],[Customer ID]],Table3[[#All],[Customer ID]],Table3[[#All],[Age]],0)} -> 52 | G4: {=_xlfn.XLOOKUP(Table4[[#This Row],[Customer ID]],Table3[[#All],[Customer ID]],Table3[[#All],[Children]],0)} -> 3 | H4: {=_xlfn.XLOOKUP(Table4[[#This Row],[Customer ID]],Table2[[#All],[Customer ID]],Table2[[#All],[BMI]],0)} -> 34.485 | I4: {=_xlfn.XLOOKUP(Table4[[#This Row],[Customer ID]],Table2[[#All],[Customer ID]],Table2[[#All],[HBA1C]],0)} -> 11.87 | J4: =_xlfn.XLOOKUP(Table4[[#This Row],[Customer ID]], 'Medical Examination'!A:A, 'Medical Examination'!D:D) -> Yes | K4: =_xlfn.XLOOKUP(Table4[[#This Row],[Customer ID]], 'Medical Examination'!A:A, 'Medical Examination'!E:E) -> No | L4: =_xlfn.XLOOKUP(Table4[[#This Row],[Customer ID]], 'Medical Examination'!A:A, 'Medical Examination'!F:F) -> No | M4: =_xlfn.XLOOKUP(Table4[[#This Row],[Customer ID]], 'Medical Examination'!A:A, 'Medical Examination'!G:G) -> 2 | N4: =_xlfn.XLOOKUP(Table4[[#This Row],[Customer ID]], 'Medical Examination'!A:A, 'Medical Examination'!H:H) -> Yes | O4: =_xlfn.XLOOKUP(Table4[[#This Row],[Customer ID]], 'Medical Examination'!A:A, 'Medical Examination'!I:I) -> Diabetes | P4: =_xlfn.XLOOKUP(Table4[[#This Row],[Customer ID]], 'Medical Examination'!A:A, 'Medical Examination'!J:J) -> Obesity | Q4: =_xlfn.XLOOKUP(Table4[[#This Row],[Customer ID]], Hospitalisation!A:A, Hospitalisation!E:E) -> 60021.4 | R4: =_xlfn.XLOOKUP(Table4[[#This Row],[Customer ID]], Hospitalisation!A:A, Hospitalisation!F:F) -> Tier - 1 | S4: =_xlfn.XLOOKUP(Table4[[#This Row],[Customer ID]], Hospitalisation!A:A, Hospitalisation!G:G) -> Tier - 1 | T4: =_xlfn.XLOOKUP(Table4[[#This Row],[Customer ID]], Hospitalisation!A:A, Hospitalisation!H:H) -> R1012 | U4: {=_xlfn.IFS(Table4[[#This Row],[Age]]<=29,"Youth",Table4[[#This Row],[Age]]<=49,"Adults",Table4[[#This Row],[Age]]>=50,"Senior")} -> Senior
A5: ID4 | B5: =_xlfn.XLOOKUP(Table4[[#This Row],[Customer ID]],Table1[[#This Row],[Customer ID]],Table1[[#This Row],[TITLE]],0) -> Ms | C5: {=_xlfn.XLOOKUP(Table4[[#This Row],[Customer ID]],Table1[[#All],[Customer ID]],Table1[[#All],[FIRST NAME]],0)} -> Kelsey | D5: {=_xlfn.XLOOKUP(Table4[[#This Row],[Customer ID]],Table1[[#All],[Customer ID]],Table1[[#All],[LAST NAME]],0)} -> Osborne | E5: {=_xlfn.XLOOKUP(Table4[[#This Row],[Customer ID]],Table3[[#All],[Customer ID]],Table3[[#All],[Date of Birth]],0)} -> 33395 | F5: {=_xlfn.XLOOKUP(Table4[[#This Row],[Customer ID]],Table3[[#All],[Customer ID]],Table3[[#All],[Age]],0)} -> 32 | G5: {=_xlfn.XLOOKUP(Table4[[#This Row],[Customer ID]],Table3[[#All],[Customer ID]],Table3[[#All],[Children]],0)} -> 1 | H5: {=_xlfn.XLOOKUP(Table4[[#This Row],[Customer ID]],Table2[[#All],[Customer ID]],Table2[[#All],[BMI]],0)} -> 38.095 | I5: {=_xlfn.XLOOKUP(Table4[[#This Row],[Customer ID]],Table2[[#All],[Customer ID]],Table2[[#All],[HBA1C]],0)} -> 6.05 | J5: =_xlfn.XLOOKUP(Table4[[#This Row],[Customer ID]], 'Medical Examination'!A:A, 'Medical Examination'!D:D) -> No | K5: =_xlfn.XLOOKUP(Table4[[#This Row],[Customer ID]], 'Medical Examination'!A:A, 'Medical Examination'!E:E) -> No | L5: =_xlfn.XLOOKUP(Table4[[#This Row],[Customer ID]], 'Medical Examination'!A:A, 'Medical Examination'!F:F) -> No | M5: =_xlfn.XLOOKUP(Table4[[#This Row],[Customer ID]], 'Medical Examination'!A:A, 'Medical Examination'!G:G) -> 0 | N5: =_xlfn.XLOOKUP(Table4[[#This Row],[Customer ID]], 'Medical Examination'!A:A, 'Medical Examination'!H:H) -> Yes | O5: =_xlfn.XLOOKUP(Table4[[#This Row],[Customer ID]], 'Medical Examination'!A:A, 'Medical Examination'!I:I) -> Prediabetes | P5: =_xlfn.XLOOKUP(Table4[[#This Row],[Customer ID]], 'Medical Examination'!A:A, 'Medical Examination'!J:J) -> Obesity | Q5: =_xlfn.XLOOKUP(Table4[[#This Row],[Customer ID]], Hospitalisation!A:A, Hospitalisation!E:E) -> 58571.07 | R5: =_xlfn.XLOOKUP(Table4[[#This Row],[Customer ID]], Hospitalisation!A:A, Hospitalisation!F:F) -> Tier - 1 | S5: =_xlfn.XLOOKUP(Table4[[#This Row],[Customer ID]], Hospitalisation!A:A, Hospitalisation!G:G) -> Tier - 3 | T5: =_xlfn.XLOOKUP(Table4[[#This Row],[Customer ID]], Hospitalisation!A:A, Hospitalisation!H:H) -> R1024 | U5: {=_xlfn.IFS(Table4[[#This Row],[Age]]<=29,"Youth",Table4[[#This Row],[Age]]<=49,"Adults",Table4[[#This Row],[Age]]>=50,"Senior")} -> Adults
A6: ID5 | B6: =_xlfn.XLOOKUP(Table4[[#This Row],[Customer ID]],Table1[[#This Row],[Customer ID]],Table1[[#This Row],[TITLE]],0) -> Ms | C6: {=_xlfn.XLOOKUP(Table4[[#This Row],[Customer ID]],Table1[[#All],[Customer ID]],Table1[[#All],[FIRST NAME]],0)} -> Kristyn | D6: {=_xlfn.XLOOKUP(Table4[[#This Row],[Customer ID]],Table1[[#All],[Customer ID]],Table1[[#All],[LAST NAME]],0)} -> Kadala | E6: {=_xlfn.XLOOKUP(Table4[[#This Row],[Customer ID]],Table3[[#All],[Customer ID]],Table3[[#All],[Date of Birth]],0)} -> 32678 | F6: {=_xlfn.XLOOKUP(Table4[[#This Row],[Customer ID]],Table3[[#All],[Customer ID]],Table3[[#All],[Age]],0)} -> 33 | G6: {=_xlfn.XLOOKUP(Table4[[#This Row],[Customer ID]],Table3[[#All],[Customer ID]],Table3[[#All],[Children]],0)} -> 0 | H6: {=_xlfn.XLOOKUP(Table4[[#This Row],[Customer ID]],Table2[[#All],[Customer ID]],Table2[[#All],[BMI]],0)} -> 35.53 | I6: {=_xlfn.XLOOKUP(Table4[[#This Row],[Customer ID]],Table2[[#All],[Customer ID]],Table2[[#All],[HBA1C]],0)} -> 5.45 | J6: =_xlfn.XLOOKUP(Table4[[#This Row],[Customer ID]], 'Medical Examination'!A:A, 'Medical Examination'!D:D) -> No | K6: =_xlfn.XLOOKUP(Table4[[#This Row],[Customer ID]], 'Medical Examination'!A:A, 'Medical Examination'!E:E) -> No | L6: =_xlfn.XLOOKUP(Table4[[#This Row],[Customer ID]], 'Medical Examination'!A:A, 'Medical Examination'!F:F) -> No | M6: =_xlfn.XLOOKUP(Table4[[#This Row],[Customer ID]], 'Medical Examination'!A:A, 'Medical Examination'!G:G) -> 0 | N6: =_xlfn.XLOOKUP(Table4[[#This Row],[Customer ID]], 'Medical Examination'!A:A, 'Medical Examination'!H:H) -> Yes | O6: =_xlfn.XLOOKUP(Table4[[#This Row],[Customer ID]], 'Medical Examination'!A:A, 'Medical Examination'!I:I) -> Normal | P6: =_xlfn.XLOOKUP(Table4[[#This Row],[Customer ID]], 'Medical Examination'!A:A, 'Medical Examination'!J:J) -> Obesity | Q6: =_xlfn.XLOOKUP(Table4[[#This Row],[Customer ID]], Hospitalisation!A:A, Hospitalisation!E:E) -> 55135.4 | R6: =_xlfn.XLOOKUP(Table4[[#This Row],[Customer ID]], Hospitalisation!A:A, Hospitalisation!F:F) -> Tier - 1 | S6: =_xlfn.XLOOKUP(Table4[[#This Row],[Customer ID]], Hospitalisation!A:A, Hospitalisation!G:G) -> Tier - 2 | T6: =_xlfn.XLOOKUP(Table4[[#This Row],[Customer ID]], Hospitalisation!A:A, Hospitalisation!H:H) -> R1012 | U6: {=_xlfn.IFS(Table4[[#This Row],[Age]]<=29,"Youth",Table4[[#This Row],[Age]]<=49,"Adults",Table4[[#This Row],[Age]]>=50,"Senior")} -> Adults
A7: ID6 | B7: =_xlfn.XLOOKUP(Table4[[#This Row],[Customer ID]],Table1[[#This Row],[Customer ID]],Table1[[#This Row],[TITLE]],0) -> Mr | C7: {=_xlfn.XLOOKUP(Table4[[#This Row],[Customer ID]],Table1[[#All],[Customer ID]],Table1[[#All],[FIRST NAME]],0)} -> Russell B | D7: {=_xlfn.XLOOKUP(Table4[[#This Row],[Customer ID]],Table1[[#All],[Customer ID]],Table1[[#All],[LAST NAME]],0)} -> Baker | E7: {=_xlfn.XLOOKUP(Table4[[#This Row],[Customer ID]],Table3[[#All],[Customer ID]],Table3[[#All],[Date of Birth]],0)} -> 22862 | F7: {=_xlfn.XLOOKUP(Table4[[#This Row],[Customer ID]],Table3[[#All],[Customer ID]],Table3[[#All],[Age]],0)} -> 60 | G7: {=_xlfn.XLOOKUP(Table4[[#This Row],[Customer ID]],Table3[[#All],[Customer ID]],Table3[[#All],[Children]],0)} -> 0 | H7: {=_xlfn.XLOOKUP(Table4[[#This Row],[Customer ID]],Table2[[#All],[Customer ID]],Table2[[#All],[BMI]],0)} -> 32.8 | I7: {=_xlfn.XLOOKUP(Table4[[#This Row],[Customer ID]],Table2[[#All],[Customer ID]],Table2[[#All],[HBA1C]],0)} -> 6.59 | J7: =_xlfn.XLOOKUP(Table4[[#This Row],[Customer ID]], 'Medical Examination'!A:A, 'Medical Examination'!D:D) -> No | K7: =_xlfn.XLOOKUP(Table4[[#This Row],[Customer ID]], 'Medical Examination'!A:A, 'Medical Examination'!E:E) -> No | L7: =_xlfn.XLOOKUP(Table4[[#This Row],[Customer ID]], 'Medical Examination'!A:A, 'Medical Examination'!F:F) -> No | M7: =_xlfn.XLOOKUP(Table4[[#This Row],[Customer ID]], 'Medical Examination'!A:A, 'Medical Examination'!G:G) -> 0 | N7: =_xlfn.XLOOKUP(Table4[[#This Row],[Customer ID]], 'Medical Examination'!A:A, 'Medical Examination'!H:H) -> Yes | O7: =_xlfn.XLOOKUP(Table4[[#This Row],[Customer ID]], 'Medical Examination'!A:A, 'Medical Examination'!I:I) -> Diabetes | P7: =_xlfn.XLOOKUP(Table4[[#This Row],[Customer ID]], 'Medical Examination'!A:A, 'Medical Examination'!J:J) -> Obesity | Q7: =_xlfn.XLOOKUP(Table4[[#This Row],[Customer ID]], Hospitalisation!A:A, Hospitalisation!E:E) -> 52590.83 | R7: =_xlfn.XLOOKUP(Table4[[#This Row],[Customer ID]], Hospitalisation!A:A, Hospitalisation!F:F) -> Tier - 1 | S7: =_xlfn.XLOOKUP(Table4[[#This Row],[Customer ID]], Hospitalisation!A:A, Hospitalisation!G:G) -> Tier - 3 | T7: =_xlfn.XLOOKUP(Table4[[#This Row],[Customer ID]], Hospitalisation!A:A, Hospitalisation!H:H) -> R1011 | U7: {=_xlfn.IFS(Table4[[#This Row],[Age]]<=29,"Youth",Table4[[#This Row],[Age]]<=49,"Adults",Table4[[#This Row],[Age]]>=50,"Senior")} -> Senior
A8: ID7 | B8: =_xlfn.XLOOKUP(Table4[[#This Row],[Customer ID]],Table1[[#This Row],[Customer ID]],Table1[[#This Row],[TITLE]],0) -> Mr | C8: {=_xlfn.XLOOKUP(Table4[[#This Row],[Customer ID]],Table1[[#All],[Customer ID]],Table1[[#All],[FIRST NAME]],0)} -> Scott | D8: {=_xlfn.XLOOKUP(Table4[[#This Row],[Customer ID]],Table1[[#All],[Customer ID]],Table1[[#All],[LAST NAME]],0)} -> Macpherson | E8: {=_xlfn.XLOOKUP(Table4[[#This Row],[Customer ID]],Table3[[#All],[Customer ID]],Table3[[#All],[Date of Birth]],0)} -> 34634 | F8: {=_xlfn.XLOOKUP(Table4[[#This Row],[Customer ID]],Table3[[#All],[Customer ID]],Table3[[#All],[Age]],0)} -> 28 | G8: {=_xlfn.XLOOKUP(Table4[[#This Row],[Customer ID]],Table3[[#All],[Customer ID]],Table3[[#All],[Children]],0)} -> 1 | H8: {=_xlfn.XLOOKUP(Table4[[#This Row],[Customer ID]],Table2[[#All],[Customer ID]],Table2[[#All],[BMI]],0)} -> 36.4 | I8: {=_xlfn.XLOOKUP(Table4[[#This Row],[Customer ID]],Table2[[#All],[Customer ID]],Table2[[#All],[HBA1C]],0)} -> 6.07 | J8: =_xlfn.XLOOKUP(Table4[[#This Row],[Customer ID]], 'Medical Examination'!A:A, 'Medical Examination'!D:D) -> No | K8: =_xlfn.XLOOKUP(Table4[[#This Row],[Customer ID]], 'Medical Examination'!A:A, 'Medical Examination'!E:E) -> No | L8: =_xlfn.XLOOKUP(Table4[[#This Row],[Customer ID]], 'Medical Examination'!A:A, 'Medical Examination'!F:F) -> No | M8: =_xlfn.XLOOKUP(Table4[[#This Row],[Customer ID]], 'Medical Examination'!A:A, 'Medical Examination'!G:G) -> 0 | N8: =_xlfn.XLOOKUP(Table4[[#This Row],[Customer ID]], 'Medical Examination'!A:A, 'Medical Examination'!H:H) -> Yes | O8: =_xlfn.XLOOKUP(Table4[[#This Row],[Customer ID]], 'Medical Examination'!A:A, 'Medical Examination'!I:I) -> Prediabetes | P8: =_xlfn.XLOOKUP(Table4[[#This Row],[Customer ID]], 'Medical Examination'!A:A, 'Medical Examination'!J:J) -> Obesity | Q8: =_xlfn.XLOOKUP(Table4[[#This Row],[Customer ID]], Hospitalisation!A:A, Hospitalisation!E:E) -> 51194.56 | R8: =_xlfn.XLOOKUP(Table4[[#This Row],[Customer ID]], Hospitalisation!A:A, Hospitalisation!F:F) -> Tier - 1 | S8: =_xlfn.XLOOKUP(Table4[[#This Row],[Customer ID]], Hospitalisation!A:A, Hospitalisation!G:G) -> Tier - 3 | T8: =_xlfn.XLOOKUP(Table4[[#This Row],[Customer ID]], Hospitalisation!A:A, Hospitalisation!H:H) -> R1011 | U8: {=_xlfn.IFS(Table4[[#This Row],[Age]]<=29,"Youth",Table4[[#This Row],[Age]]<=49,"Adults",Table4[[#This Row],[Age]]>=50,"Senior")} -> Youth
A9: ID8 | B9: =_xlfn.XLOOKUP(Table4[[#This Row],[Customer ID]],Table1[[#This Row],[Customer ID]],Table1[[#This Row],[TITLE]],0) -> Mr | C9: {=_xlfn.XLOOKUP(Table4[[#This Row],[Customer ID]],Table1[[#All],[Customer ID]],Table1[[#All],[FIRST NAME]],0)} -> Stephen | D9: {=_xlfn.XLOOKUP(Table4[[#This Row],[Customer ID]],Table1[[#All],[Customer ID]],Table1[[#All],[LAST NAME]],0)} -> Hallman | E9: {=_xlfn.XLOOKUP(Table4[[#This Row],[Customer ID]],Table3[[#All],[Customer ID]],Table3[[#All],[Date of Birth]],0)} -> 21363 | F9: {=_xlfn.XLOOKUP(Table4[[#This Row],[Customer ID]],Table3[[#All],[Customer ID]],Table3[[#All],[Age]],0)} -> 64 | G9: {=_xlfn.XLOOKUP(Table4[[#This Row],[Customer ID]],Table3[[#All],[Customer ID]],Table3[[#All],[Children]],0)} -> 2 | H9: {=_xlfn.XLOOKUP(Table4[[#This Row],[Customer ID]],Table2[[#All],[Customer ID]],Table2[[#All],[BMI]],0)} -> 36.96 | I9: {=_xlfn.XLOOKUP(Table4[[#This Row],[Customer ID]],Table2[[#All],[Customer ID]],Table2[[#All],[HBA1C]],0)} -> 7.93 | J9: =_xlfn.XLOOKUP(Table4[[#This Row],[Customer ID]], 'Medical Examination'!A:A, 'Medical Examination'!D:D) -> No | K9: =_xlfn.XLOOKUP(Table4[[#This Row],[Customer ID]], 'Medical Examination'!A:A, 'Medical Examination'!E:E) -> No | L9: =_xlfn.XLOOKUP(Table4[[#This Row],[Customer ID]], 'Medical Examination'!A:A, 'Medical Examination'!F:F) -> No | M9: =_xlfn.XLOOKUP(Table4[[#This Row],[Customer ID]], 'Medical Examination'!A:A, 'Medical Examination'!G:G) -> 3 | N9: =_xlfn.XLOOKUP(Table4[[#This Row],[Customer ID]], 'Medical Examination'!A:A, 'Medical Examination'!H:H) -> Yes | O9: =_xlfn.XLOOKUP(Table4[[#This Row],[Customer ID]], 'Medical Examination'!A:A, 'Medical Examination'!I:I) -> Diabetes | P9: =_xlfn.XLOOKUP(Table4[[#This Row],[Customer ID]], 'Medical Examination'!A:A, 'Medical Examination'!J:J) -> Obesity | Q9: =_xlfn.XLOOKUP(Table4[[#This Row],[Customer ID]], Hospitalisation!A:A, Hospitalisation!E:E) -> 49577.66 | R9: =_xlfn.XLOOKUP(Table4[[#This Row],[Customer ID]], Hospitalisation!A:A, Hospitalisation!F:F) -> Tier - 2 | S9: =_xlfn.XLOOKUP(Table4[[#This Row],[Customer ID]], Hospitalisation!A:A, Hospitalisation!G:G) -> Tier - 2 | T9: =_xlfn.XLOOKUP(Table4[[#This Row],[Customer ID]], Hospitalisation!A:A, Hospitalisation!H:H) -> R1013 | U9: {=_xlfn.IFS(Table4[[#This Row],[Age]]<=29,"Youth",Table4[[#This Row],[Age]]<=49,"Adults",Table4[[#This Row],[Age]]>=50,"Senior")} -> Senior
A10: ID9 | B10: =_xlfn.XLOOKUP(Table4[[#This Row],[Customer ID]],Table1[[#This Row],[Customer ID]],Table1[[#This Row],[TITLE]],0) -> Mr | C10: {=_xlfn.XLOOKUP(Table4[[#This Row],[Customer ID]],Table1[[#All],[Customer ID]],Table1[[#All],[FIRST NAME]],0)} -> Patrick R | D10: {=_xlfn.XLOOKUP(Table4[[#This Row],[Customer ID]],Table1[[#All],[Customer ID]],Table1[[#All],[LAST NAME]],0)} -> Moran | E10: {=_xlfn.XLOOKUP(Table4[[#This Row],[Customer ID]],Table3[[#All],[Customer ID]],Table3[[#All],[Date of Birth]],0)} -> 23258 | F10: {=_xlfn.XLOOKUP(Table4[[#This Row],[Customer ID]],Table3[[#All],[Customer ID]],Table3[[#All],[Age]],0)} -> 59 | G10: {=_xlfn.XLOOKUP(Table4[[#This Row],[Customer ID]],Table3[[#All],[Customer ID]],Table3[[#All],[Children]],0)} -> 1 | H10: {=_xlfn.XLOOKUP(Table4[[#This Row],[Customer ID]],Table2[[#All],[Customer ID]],Table2[[#All],[BMI]],0)} -> 41.14 | I10: {=_xlfn.XLOOKUP(Table4[[#This Row],[Customer ID]],Table2[[#All],[Customer ID]],Table2[[#All],[HBA1C]],0)} -> 9.58 | J10: =_xlfn.XLOOKUP(Table4[[#This Row],[Customer ID]], 'Medical Examination'!A:A, 'Medical Examination'!D:D) -> Yes | K10: =_xlfn.XLOOKUP(Table4[[#This Row],[Customer ID]], 'Medical Examination'!A:A, 'Medical Examination'!E:E) -> No | L10: =_xlfn.XLOOKUP(Table4[[#This Row],[Customer ID]], 'Medical Examination'!A:A, 'Medical Examination'!F:F) -> Yes | M10: =_xlfn.XLOOKUP(Table4[[#This Row],[Customer ID]], 'Medical Examination'!A:A, 'Medical Examination'!G:G) -> 1 | N10: =_xlfn.XLOOKUP(Table4[[#This Row],[Customer ID]], 'Medical Examination'!A:A, 'Medical Examination'!H:H) -> Yes | O10: =_xlfn.XLOOKUP(Table4[[#This Row],[Customer ID]], 'Medical Examination'!A:A, 'Medical Examination'!I:I) -> Diabetes | P10: =_xlfn.XLOOKUP(Table4[[#This Row],[Customer ID]], 'Medical Examination'!A:A, 'Medical Examination'!J:J) -> Obesity | Q10: =_xlfn.XLOOKUP(Table4[[#This Row],[Customer ID]], Hospitalisation!A:A, Hospitalisation!E:E) -> 48970.25 | R10: =_xlfn.XLOOKUP(Table4[[#This Row],[Customer ID]], Hospitalisation!A:A, Hospitalisation!F:F) -> Tier - 1 | S10: =_xlfn.XLOOKUP(Table4[[#This Row],[Customer ID]], Hospitalisation!A:A, Hospitalisation!G:G) -> Tier - 2 | T10: =_xlfn.XLOOKUP(Table4[[#This Row],[Customer ID]], Hospitalisation!A:A, Hospitalisation!H:H) -> R1013 | U10: {=_xlfn.IFS(Table4[[#This Row],[Age]]<=29,"Youth",Table4[[#This Row],[Age]]<=49,"Adults",Table4[[#This Row],[Age]]>=50,"Senior")} -> Senior
A11: ID10 | B11: =_xlfn.XLOOKUP(Table4[[#This Row],[Customer ID]],Table1[[#This Row],[Customer ID]],Table1[[#This Row],[TITLE]],0) -> Ms | C11: {=_xlfn.XLOOKUP(Table4[[#This Row],[Customer ID]],Table1[[#All],[Customer ID]],Table1[[#All],[FIRST NAME]],0)} -> Brooke N | D11: {=_xlfn.XLOOKUP(Table4[[#This Row],[Customer ID]],Table1[[#All],[Customer ID]],Table1[[#All],[LAST NAME]],0)} -> Benner | E11: {=_xlfn.XLOOKUP(Table4[[#This Row],[Customer ID]],Table3[[#All],[Customer ID]],Table3[[#All],[Date of Birth]],0)} -> 28853 | F11: {=_xlfn.XLOOKUP(Table4[[#This Row],[Customer ID]],Table3[[#All],[Customer ID]],Table3[[#All],[Age]],0)} -> 44 | G11: {=_xlfn.XLOOKUP(Table4[[#This Row],[Customer ID]],Table3[[#All],[Customer ID]],Table3[[#All],[Children]],0)} -> 0 | H11: {=_xlfn.XLOOKUP(Table4[[#This Row],[Customer ID]],Table2[[#All],[Customer ID]],Table2[[#All],[BMI]],0)} -> 38.06 | I11: {=_xlfn.XLOOKUP(Table4[[#This Row],[Customer ID]],Table2[[#All],[Customer ID]],Table2[[#All],[HBA1C]],0)} -> 10.79 | J11: =_xlfn.XLOOKUP(Table4[[#This Row],[Customer ID]], 'Medical Examination'!A:A, 'Medical Examination'!D:D) -> No | K11: =_xlfn.XLOOKUP(Table4[[#This Row],[Customer ID]], 'Medical Examination'!A:A, 'Medical Examination'!E:E) -> No | L11: =_xlfn.XLOOKUP(Table4[[#This Row],[Customer ID]], 'Medical Examination'!A:A, 'Medical Examination'!F:F) -> No | M11: =_xlfn.XLOOKUP(Table4[[#This Row],[Customer ID]], 'Medical Examination'!A:A, 'Medical Examination'!G:G) -> 0 | N11: =_xlfn.XLOOKUP(Table4[[#This Row],[Customer ID]], 'Medical Examination'!A:A, 'Medical Examination'!H:H) -> Yes | O11: =_xlfn.XLOOKUP(Table4[[#This Row],[Customer ID]], 'Medical Examination'!A:A, 'Medical Examination'!I:I) -> Diabetes | P11: =_xlfn.XLOOKUP(Table4[[#This Row],[Customer ID]], 'Medical Examination'!A:A, 'Medical Examination'!J:J) -> Obesity | Q11: =_xlfn.XLOOKUP(Table4[[#This Row],[Customer ID]], Hospitalisation!A:A, Hospitalisation!E:E) -> 48885.14 | R11: =_xlfn.XLOOKUP(Table4[[#This Row],[Customer ID]], Hospitalisation!A:A, Hospitalisation!F:F) -> Tier - 1 | S11: =_xlfn.XLOOKUP(Table4[[#This Row],[Customer ID]], Hospitalisation!A:A, Hospitalisation!G:G) -> Tier - 2 | T11: =_xlfn.XLOOKUP(Table4[[#This Row],[Customer ID]], Hospitalisation!A:A, Hospitalisation!H:H) -> R1013 | U11: {=_xlfn.IFS(Table4[[#This Row],[Age]]<=29,"Youth",Table4[[#This Row],[Age]]<=49,"Adults",Table4[[#This Row],[Age]]>=50,"Senior")} -> Adults
A12: ID11 | B12: =_xlfn.XLOOKUP(Table4[[#This Row],[Customer ID]],Table1[[#This Row],[Customer ID]],Table1[[#This Row],[TITLE]],0) -> Ms | C12: {=_xlfn.XLOOKUP(Table4[[#This Row],[Customer ID]],Table1[[#All],[Customer ID]],Table1[[#All],[FIRST NAME]],0)} -> Paola Andrea | D12: {=_xlfn.XLOOKUP(Table4[[#This Row],[Customer ID]],Table1[[#All],[Customer ID]],Table1[[#All],[LAST NAME]],0)} -> Fierro Vargas | E12: {=_xlfn.XLOOKUP(Table4[[#This Row],[Customer ID]],Table3[[#All],[Customer ID]],Table3[[#All],[Date of Birth]],0)} -> 21753 | F12: {=_xlfn.XLOOKUP(Table4[[#This Row],[Customer ID]],Table3[[#All],[Customer ID]],Table3[[#All],[Age]],0)} -> 63 | G12: {=_xlfn.XLOOKUP(Table4[[#This Row],[Customer ID]],Table3[[#All],[Customer ID]],Table3[[#All],[Children]],0)} -> 0 | H12: {=_xlfn.XLOOKUP(Table4[[#This Row],[Customer ID]],Table2[[#All],[Customer ID]],Table2[[#All],[BMI]],0)} -> 37.7 | I12: {=_xlfn.XLOOKUP(Table4[[#This Row],[Customer ID]],Table2[[#All],[Customer ID]],Table2[[#All],[HBA1C]],0)} -> 5.96 | J12: =_xlfn.XLOOKUP(Table4[[#This Row],[Customer ID]], 'Medical Examination'!A:A, 'Medical Examination'!D:D) -> Yes | K12: =_xlfn.XLOOKUP(Table4[[#This Row],[Customer ID]], 'Medical Examination'!A:A, 'Medical Examination'!E:E) -> No | L12: =_xlfn.XLOOKUP(Table4[[#This Row],[Customer ID]], 'Medical Examination'!A:A, 'Medical Examination'!F:F) -> No | M12: =_xlfn.XLOOKUP(Table4[[#This Row],[Customer ID]], 'Medical Examination'!A:A, 'Medical Examination'!G:G) -> 2 | N12: =_xlfn.XLOOKUP(Table4[[#This Row],[Customer ID]], 'Medical Examination'!A:A, 'Medical Examination'!H:H) -> Yes | O12: =_xlfn.XLOOKUP(Table4[[#This Row],[Customer ID]], 'Medical Examination'!A:A, 'Medical Examination'!I:I) -> Prediabetes | P12: =_xlfn.XLOOKUP(Table4[[#This Row],[Customer ID]], 'Medical Examination'!A:A, 'Medical Examination'!J:J) -> Obesity | Q12: =_xlfn.XLOOKUP(Table4[[#This Row],[Customer ID]], Hospitalisation!A:A, Hospitalisation!E:E) -> 48824.45 | R12: =_xlfn.XLOOKUP(Table4[[#This Row],[Customer ID]], Hospitalisation!A:A, Hospitalisation!F:F) -> Tier - 2 | S12: =_xlfn.XLOOKUP(Table4[[#This Row],[Customer ID]], Hospitalisation!A:A, Hospitalisation!G:G) -> Tier - 1 | T12: =_xlfn.XLOOKUP(Table4[[#This Row],[Customer ID]], Hospitalisation!A:A, Hospitalisation!H:H) -> R1011 | U12: {=_xlfn.IFS(Table4[[#This Row],[Age]]<=29,"Youth",Table4[[#This Row],[Age]]<=49,"Adults",Table4[[#This Row],[Age]]>=50,"Senior")} -> Senior
A13: ID12 | B13: =_xlfn.XLOOKUP(Table4[[#This Row],[Customer ID]],Table1[[#This Row],[Customer ID]],Table1[[#This Row],[TITLE]],0) -> Mr | C13: {=_xlfn.XLOOKUP(Table4[[#This Row],[Customer ID]],Table1[[#All],[Customer ID]],Table1[[#All],[FIRST NAME]],0)} -> David | D13: {=_xlfn.XLOOKUP(Table4[[#This Row],[Customer ID]],Table1[[#All],[Customer ID]],Table1[[#All],[LAST NAME]],0)} -> Franz | E13: {=_xlfn.XLOOKUP(Table4[[#This Row],[Customer ID]],Table3[[#All],[Customer ID]],Table3[[#All],[Date of Birth]],0)} -> 24042 | F13: {=_xlfn.XLOOKUP(Table4[[#This Row],[Customer ID]],Table3[[#All],[Customer ID]],Table3[[#All],[Age]],0)} -> 57 | G13: {=_xlfn.XLOOKUP(Table4[[#This Row],[Customer ID]],Table3[[#All],[Customer ID]],Table3[[#All],[Children]],0)} -> 1 | H13: {=_xlfn.XLOOKUP(Table4[[#This Row],[Customer ID]],Table2[[#All],[Customer ID]],Table2[[#All],[BMI]],0)} -> 42.13 | I13: {=_xlfn.XLOOKUP(Table4[[#This Row],[Customer ID]],Table2[[#All],[Customer ID]],Table2[[#All],[HBA1C]],0)} -> 11.9 | J13: =_xlfn.XLOOKUP(Table4[[#This Row],[Customer ID]], 'Medical Examination'!A:A, 'Medical Examination'!D:D) -> No | K13: =_xlfn.XLOOKUP(Table4[[#This Row],[Customer ID]], 'Medical Examination'!A:A, 'Medical Examination'!E:E) -> No | L13: =_xlfn.XLOOKUP(Table4[[#This Row],[Customer ID]], 'Medical Examination'!A:A, 'Medical Examination'!F:F) -> No | M13: =_xlfn.XLOOKUP(Table4[[#This Row],[Customer ID]], 'Medical Examination'!A:A, 'Medical Examination'!G:G) -> 0 | N13: =_xlfn.XLOOKUP(Table4[[#This Row],[Customer ID]], 'Medical Examination'!A:A, 'Medical Examination'!H:H) -> Yes | O13: =_xlfn.XLOOKUP(Table4[[#This Row],[Customer ID]], 'Medical Examination'!A:A, 'Medical Examination'!I:I) -> Diabetes | P13: =_xlfn.XLOOKUP(Table4[[#This Row],[Customer ID]], 'Medical Examination'!A:A, 'Medical Examination'!J:J) -> Obesity | Q13: =_xlfn.XLOOKUP(Table4[[#This Row],[Customer ID]], Hospitalisation!A:A, Hospitalisation!E:E) -> 48675.52 | R13: =_xlfn.XLOOKUP(Table4[[#This Row],[Customer ID]], Hospitalisation!A:A, Hospitalisation!F:F) -> Tier - 1 | S13: =_xlfn.XLOOKUP(Table4[[#This Row],[Customer ID]], Hospitalisation!A:A, Hospitalisation!G:G) -> Tier - 2 | T13: =_xlfn.XLOOKUP(Table4[[#This Row],[Customer ID]], Hospitalisation!A:A, Hospitalisation!H:H) -> R1013 | U13: {=_xlfn.IFS(Table4[[#This Row],[Age]]<=29,"Youth",Table4[[#This Row],[Age]]<=49,"Adults",Table4[[#This Row],[Age]]>=50,"Senior")} -> Senior
... A2336: ID2335 | B2336: =_xlfn.XLOOKUP(Table4[[#This Row],[Customer ID]],Table1[[#This Row],[Customer ID]],Table1[[#This Row],[TITLE]],0) -> Mr | C2336: {=_xlfn.XLOOKUP(Table4[[#This Row],[Customer ID]],Table1[[#All],[Customer ID]],Table1[[#All],[FIRST NAME]],0)} -> Aaron K | D2336: {=_xlfn.XLOOKUP(Table4[[#This Row],[Customer ID]],Table1[[#All],[Customer ID]],Table1[[#All],[LAST NAME]],0)} -> German | E2336: {=_xlfn.XLOOKUP(Table4[[#This Row],[Customer ID]],Table3[[#All],[Customer ID]],Table3[[#All],[Date of Birth]],0)} -> 33794 | F2336: {=_xlfn.XLOOKUP(Table4[[#This Row],[Customer ID]],Table3[[#All],[Customer ID]],Table3[[#All],[Age]],0)} -> 30 | G2336: {=_xlfn.XLOOKUP(Table4[[#This Row],[Customer ID]],Table3[[#All],[Customer ID]],Table3[[#All],[Children]],0)} -> 0 | H2336: {=_xlfn.XLOOKUP(Table4[[#This Row],[Customer ID]],Table2[[#All],[Customer ID]],Table2[[#All],[BMI]],0)} -> 17.58 | I2336: {=_xlfn.XLOOKUP(Table4[[#This Row],[Customer ID]],Table2[[#All],[Customer ID]],Table2[[#All],[HBA1C]],0)} -> 4.51 | J2336: =_xlfn.XLOOKUP(Table4[[#This Row],[Customer ID]], 'Medical Examination'!A:A, 'Medical Examination'!D:D) -> No | K2336: =_xlfn.XLOOKUP(Table4[[#This Row],[Customer ID]], 'Medical Examination'!A:A, 'Medical Examination'!E:E) -> No | L2336: =_xlfn.XLOOKUP(Table4[[#This Row],[Customer ID]], 'Medical Examination'!A:A, 'Medical Examination'!F:F) -> No | M2336: =_xlfn.XLOOKUP(Table4[[#This Row],[Customer ID]], 'Medical Examination'!A:A, 'Medical Examination'!G:G) -> 1 | N2336: =_xlfn.XLOOKUP(Table4[[#This Row],[Customer ID]], 'Medical Examination'!A:A, 'Medical Examination'!H:H) -> No | O2336: =_xlfn.XLOOKUP(Table4[[#This Row],[Customer ID]], 'Medical Examination'!A:A, 'Medical Examination'!I:I) -> Normal | P2336: =_xlfn.XLOOKUP(Table4[[#This Row],[Customer ID]], 'Medical Examination'!A:A, 'Medical Examination'!J:J) -> Underweight | Q2336: =_xlfn.XLOOKUP(Table4[[#This Row],[Customer ID]], Hospitalisation!A:A, Hospitalisation!E:E) -> 563.84 | R2336: =_xlfn.XLOOKUP(Table4[[#This Row],[Customer ID]], Hospitalisation!A:A, Hospitalisation!F:F) -> Tier - 2 | S2336: =_xlfn.XLOOKUP(Table4[[#This Row],[Customer ID]], Hospitalisation!A:A, Hospitalisation!G:G) -> Tier - 3 | T2336: =_xlfn.XLOOKUP(Table4[[#This Row],[Customer ID]], Hospitalisation!A:A, Hospitalisation!H:H) -> R1013 | U2336: {=_xlfn.IFS(Table4[[#This Row],[Age]]<=29,"Youth",Table4[[#This Row],[Age]]<=49,"Adults",Table4[[#This Row],[Age]]>=50,"Senior")} -> Adults

Sheet Healthcare Analysis Using AI
A1: Metric | B1: Value
A2: Total Customers | B2: =COUNTA('Health Care'!A:A)-1 -> 2335
A3: Total Hospitalisation Count | B3: =COUNTA('Health Care'!A:A)-1 -> 2335
A4: Total Healthcare Costs | B4: =SUM('Health Care'!Q1:Q2336) -> 31592359
A5: Average Healthcare Costs | B5: =AVERAGE('Health Care'!Q1:Q2336) -> 13529.918
A6: Average BMI | B6: =AVERAGE('Health Care'!H1:H2336) -> 30.972645
A7: Average HBA1C | B7: =AVERAGE('Health Care'!I1:I2336) -> 6.5789979
A8: Average Surgeries | B8: =AVERAGE('Health Care'!M1:M2336) -> 0.67623126

Sheet Insight And Analysis
J1: INSIGHTS AND ANALYSIS
J6: Smokers with Cancer History (Pie Chart)
J8: ü Analysed with the given population count, there is only 391 individuals who has cancer history and are smoker ("Yes"). Meanwhile, majority 1944 are do not have cancer and are smoker ("No").
J9: ü This shows that, within the specific data of smokers, the number of individuals without a cancer history is higher than those with a cancer history.
J12: ü This suggest that, in this dataset, the majority of samples are smokers without a cancer history.
J17: Charges By Weight Status (Bar Chart)
J20: ü This bar chart detailing "charges by weight status" clearly shows the difference in charges across 4 categories.
J22: ü This data clearly indicating that obese customers are highly associated charges by significant margin, cost of $2,03,43,646. This charge is higher than other categories.
J24: ü The other three categories are displayed: Overweight , Normal Weight, Underweight.
J26: ü Charges for the overweight status are $57,29,141. Charges For the Normalweight status are $43,05,290 and The underweight status Charges are $12,14,279
J28: ü Since within the dataset obesity represents the greatest financial cost among the measured healthmetrics.

Sheet Pivot Table
A2: Weight Stuatus | B2: Sum of Charges | D2: Count of hospital tire | E2: HBA1C Result
A3: Normal Weight | B3: 1719974.8 | D3: Row Labels | E3: Normal
A4: Obesity | B4: 8574902.7 | D4: Tier - 1 | E4: 139
A5: Overweight | B5: 2455836.9 | D5: Tier - 2 | E5: 676
A6: Underweight | B6: 566702.46 | D6: Tier - 3 | E6: 288
A10: Hospital Tire | B10: Sum of Charges | D10: Count of HBA1C Result | E10: Column Labels
A11: Tier - 1 | B11: 3761763.3 | D11: HBA1C Result | E11: Normal
A12: Tier - 2 | B12: 7038071.2 | D12: Adults | E12: 480
A13: Tier - 3 | B13: 2517582.3 | D13: Senior | E13: 168
D14: Youth | E14: 455
A17: HBA1C Result | B17: Sum of No. of Surgeries | D17: Sum of No. of Surgeries | E17: Column Labels
A18: Normal | B18: 783 | D18: Row Labels | E18: Tier - 1 | F18: Tier - 2 | G18: Tier - 3
D19: Tier - 1 | E19: 24 | F19: 27 | G19: 42
D20: Tier - 2 | E20: 128 | F20: 161 | G20: 163
D21: Tier - 3 | E21: 82 | F21: 72 | G21: 84
A23: HBA1C Result | B23: Sum of Charges
A24: Normal | B24: 13317417
D25: Count of Age Group | E25: Column Labels
D26: Row Labels | E26: No | F26: Yes
D27: Adults | E27: 336 | F27: 144
D28: Senior | E28: 41 | F28: 127
A29: Cancer History | B29: Count of SMOKER | D29: Youth | E29: 293 | F29: 162
A30: No | B30: 1944
A31: Yes | B31: 391

Sheet Dashboard
A1: HEALTHCARE PREDICTIVE ANALYSIS DASHBOARD WITH AI
